buildstream/__init__.py
buildstream/__main__.py
buildstream/_artifact.py
buildstream/_artifactcache.py
buildstream/_artifactelement.py
buildstream/_artifactproject.py
buildstream/_assetcache.py
buildstream/_cachekey.py
buildstream/_context.py
buildstream/_elementproxy.py
buildstream/_elementsources.py
buildstream/_elementsourcescache.py
buildstream/_exceptions.py
buildstream/_includes.py
buildstream/_message.py
buildstream/_messenger.py
buildstream/_overlapcollector.py
buildstream/_pipeline.py
buildstream/_pluginproxy.py
buildstream/_profile.py
buildstream/_project.py
buildstream/_projectrefs.py
buildstream/_remote.py
buildstream/_remotespec.py
buildstream/_signals.py
buildstream/_site.py
buildstream/_sourcecache.py
buildstream/_state.py
buildstream/_stream.py
buildstream/_types.cpython-313-x86_64-linux-gnu.so
buildstream/_types.pyi
buildstream/_utils.cpython-313-x86_64-linux-gnu.so
buildstream/_utils.pyi
buildstream/_variables.cpython-313-x86_64-linux-gnu.so
buildstream/_variables.pyi
buildstream/_version.py
buildstream/_versions.py
buildstream/_workspaces.py
buildstream/_yaml.cpython-313-x86_64-linux-gnu.so
buildstream/_yaml.pyi
buildstream/buildelement.py
buildstream/downloadablefilesource.py
buildstream/element.py
buildstream/exceptions.py
buildstream/node.cpython-313-x86_64-linux-gnu.so
buildstream/node.pyi
buildstream/plugin.py
buildstream/py.typed
buildstream/scriptelement.py
buildstream/source.py
buildstream/sourcemirror.py
buildstream/types.py
buildstream/utils.py
buildstream/_cas/__init__.py
buildstream/_cas/cascache.py
buildstream/_cas/casdprocessmanager.py
buildstream/_cas/casremote.py
buildstream/_cas/casserver.py
buildstream/_frontend/__init__.py
buildstream/_frontend/app.py
buildstream/_frontend/cli.py
buildstream/_frontend/complete.py
buildstream/_frontend/linuxapp.py
buildstream/_frontend/profile.py
buildstream/_frontend/status.py
buildstream/_frontend/widget.py
buildstream-2.6.0.dist-info/METADATA
buildstream-2.6.0.dist-info/WHEEL
buildstream-2.6.0.dist-info/entry_points.txt
buildstream-2.6.0.dist-info/top_level.txt
buildstream-2.6.0.dist-info/RECORD
buildstream-2.6.0.dist-info/licenses/LICENSE
buildstream-2.6.0.dist-info/licenses/NOTICE
