Metadata-Version: 2.4
Name: BuildStream
Version: 2.6.0
Summary: A framework for modelling build pipelines in YAML
Home-page: https://buildstream.build
Author: The Apache Software Foundation
Author-email: dev@buildstream.apache.org
License: Apache License Version 2.0
Project-URL: Source, https://github.com/apache/buildstream
Project-URL: Documentation, https://docs.buildstream.build
Project-URL: Tracker, https://github.com/apache/buildstream/issues
Project-URL: Mailing List, https://lists.apache.org/list.html?dev@buildstream.apache.org
Classifier: Environment :: Console
Classifier: Intended Audience :: Developers
Classifier: License :: OSI Approved :: Apache Software License
Classifier: Operating System :: POSIX
Classifier: Programming Language :: Python :: 3
Classifier: Programming Language :: Python :: 3.9
Classifier: Programming Language :: Python :: 3.10
Classifier: Programming Language :: Python :: 3.11
Classifier: Programming Language :: Python :: 3.12
Classifier: Programming Language :: Python :: 3.13
Classifier: Programming Language :: Python :: 3.14
Classifier: Topic :: Software Development :: Build Tools
Requires-Python: ~=3.9
License-File: LICENSE
License-File: NOTICE
Requires-Dist: Click!=8.2.2,>=7.0
Requires-Dist: grpcio
Requires-Dist: Jinja2>=2.10
Requires-Dist: importlib_metadata>=3.6; python_version < "3.10"
Requires-Dist: packaging
Requires-Dist: pluginbase
Requires-Dist: protobuf<9,>=5.29
Requires-Dist: psutil
Requires-Dist: ruamel.yaml>=0.16.7
Requires-Dist: ruamel.yaml.clib>=0.1.2
Requires-Dist: pyroaring
Requires-Dist: ujson
Dynamic: author
Dynamic: author-email
Dynamic: classifier
Dynamic: description
Dynamic: description-content-type
Dynamic: home-page
Dynamic: license
Dynamic: license-file
Dynamic: project-url
Dynamic: requires-dist
Dynamic: requires-python
Dynamic: summary
